turing/__init__.py
xtuning-0.0.0.dist-info/LICENSE
xtuning-0.0.0.dist-info/METADATA
xtuning-0.0.0.dist-info/WHEEL
xtuning-0.0.0.dist-info/top_level.txt
xtuning-0.0.0.dist-info/RECORD
