Metadata-Version: 2.1
Name: xtuning
Version: 0.0.0
Summary: Fine-tuning, evaluation and data generation for LLMs
Author-email: Glenn Ko <glenn@stochastic.ai>, Yuji Chai <yuji.chai@stochastic.ai>, Roman Ageev <roman.ageev@stochastic.ai>, Toan Do <toan.do@stochastic.ai>, Marcos R M <marcos.rm@stochastic.ai>, Sarthak Langde <sarthak.langde@stochastic.ai>, Riccardo Romagnoli <riccardo.romagnoli@stochastic.ai>, Subhash G N <subhash.gn@stochastic.ai>
License: Apache License
Project-URL: homepage, https://turing.stochastic.ai/
Project-URL: documentation, https://github.com/stochasticai/turing-docs
Project-URL: repository, https://github.com/stochasticai/turing
Keywords: nlp,llm,finetuning,evaluation,data-generation,training,distributed
Classifier: Development Status :: 3 - Alpha
Classifier: Intended Audience :: Developers
Classifier: Intended Audience :: Science/Research
Classifier: License :: OSI Approved :: Apache Software License
Classifier: Programming Language :: Python :: 3
Classifier: Programming Language :: Python :: 3.6
Classifier: Programming Language :: Python :: 3.7
Classifier: Programming Language :: Python :: 3.8
Classifier: Programming Language :: Python :: 3.9
Classifier: Topic :: Scientific/Engineering :: Artificial Intelligence
Classifier: Topic :: Scientific/Engineering :: Information Analysis
Classifier: Topic :: Software Development :: Libraries :: Python Modules
Classifier: Topic :: Text Processing :: Linguistic
Requires-Python: >=3.6
License-File: LICENSE
Requires-Dist: torch (>=1.9.0)
Requires-Dist: pytorch-lightning
Requires-Dist: transformers
Requires-Dist: datasets
Requires-Dist: evaluate
Requires-Dist: peft
